image_finder/__init__.py
image_finder/core/__init__.py
image_finder/core/finder.py
image_finder-0.0.1.dist-info/LICENSE
image_finder-0.0.1.dist-info/METADATA
image_finder-0.0.1.dist-info/WHEEL
image_finder-0.0.1.dist-info/top_level.txt
image_finder-0.0.1.dist-info/RECORD
