Metadata-Version: 2.1
Name: image-finder
Version: 0.0.1
Summary: Image-finder is an OpenCV-based Python3 package that locates image and extracts text in a range.
Author-email: minwook-shin <minwook0106@gmail.com>
Project-URL: Homepage, https://github.com/minwook-shin/image-finder
Project-URL: Bug Tracker, https://github.com/minwook-shin/image-finder/issues
Classifier: Programming Language :: Python :: 3
Classifier: License :: OSI Approved :: Apache Software License
Classifier: Operating System :: OS Independent
Requires-Python: >=3.9
License-File: LICENSE
Requires-Dist: opencv-python-headless ==4.9.0.80
Requires-Dist: easyocr ==1.7.1
Requires-Dist: numpy ==1.26.4
Provides-Extra: dev
Requires-Dist: build ==1.1.1 ; extra == 'dev'
